{
  "metadata": {
    "description": "Smaller SFT source prompt config derived from grpo_source_v4_mixed.json, keeping the same prompt distribution with fewer prompts per config.",
    "derived_from": "experiments/configs/grpo_source_v4_mixed.json",
    "notes": [
      "This config is intended for building a lighter source CSV for SFT.",
      "Prompt styles, graph set, and reasoning guidance mix match the GRPO source config.",
      "Only the dataset generation size is reduced."
    ]
  },
  "dataset_generation": {
    "graphs_dir": "causal_graphs/real_data/small_graphs",
    "graph_names": [
      "earthquake",
      "asia",
      "sachs"
    ],
    "num_prompts_per_config": 2,
    "seed": 42,
    "reasoning_guidances": [
      "concise",
      "none"
    ]
  },
  "config_defaults": {
    "wrapper_mode": "chat",
    "append_format_hint": true,
    "row_order": "random",
    "col_order": "random",
    "col_perms": 4,
    "shuffles_per_graph": 1
  },
  "config_product": {
    "prompt_style": [
      "summary",
      "matrix"
    ],
    "obs_per_prompt": [
      100,
      1000
    ],
    "int_per_combo": [
      10,
      50
    ],
    "anonymize": [
      false,
      true
    ]
  }
}
